{
  "1HN": "https://us1hnapp.iugocare.com",
  "Alpha": "https://usalphaapp.iugocare.com",
  "Armstrong": "https://usarmstrongapp.iugocare.com",
  "Biorhythms": "https://usbiorhythmsapp.iugocare.com",
  "BrushCountry": "https://usbrushapp.iugocare.com",
  "Candanosa": "https://uscandanosaapp.iugocare.com",
  "CareGuardian": "https://uscareguardianapp.iugocare.com",
  "Champion": "https://uschampionapp.iugocare.com",
  "DigiiMed": "https://usdigiimedapp.iugocare.com",
  "Divinas": "https://usdivinasapp.iugocare.com",
  "Esperanza": "https://usesperanzaapp.iugocare.com",
  "Frederikstedhc": "https://usfrederikstedhcapp.iugocare.com",
  "Garcia": "https://usgarciaapp.iugocare.com",
  "Haber": "https://ushaberapp.iugocare.com",
  "HDPTC": "https://ushdptcapp.iugocare.com",
  "Holt": "https://usholtapp.iugocare.com",
  "HealingHands": "https://ushhapp.iugocare.com",
  "HomeHealthCheck": "https://ushhcapp.iugocare.com",
  "JustCardio": "https://usheartapp.iugocare.com",
  "Kardio": "https://uskardiohealthapp.iugocare.com",
  "Maxlink": "https://usmaxlinkapp.iugocare.com",
  "NewConcept": "https://usnewconceptapp.iugocare.com",
  "NSCL": "https://usnsclapp.iugocare.com",
  "Ochoa": "https://usochoaapp.iugocare.com",
  "Paleracio": "https://uspaleracioapp.iugocare.com",
  "Pean": "https://uspeanapp.iugocare.com",
  "Posluszny": "https://usposlusznyapp.iugocare.com",
  "Proactive": "https://usproactiveapp.iugocare.com",
  "PTL": "https://usptlapp.iugocare.com",
  "Regal": "https://usregalapp.iugocare.com",
  "Reliq": "https://usprodapp.iugocare.com",
  "ReliqRPM": "https://usreliqrpmapp.iugocare.com",
  "RioGrande": "https://usriograndeapp.iugocare.com",
  "Salud": "https://ussaludapp.iugocare.com",
  "SanBenito": "https://ussanbenitoapp.iugocare.com",
  "Serenity": "https://usserenityapp.iugocare.com",
  "StarOrtho": "https://usstarorthoapp.iugocare.com",
  "Sunshine": "https://ussunshineapp.iugocare.com",
  "Tavarez": "https://ustavarezapp.iugocare.com",
  "Training": "https://ustrainingapp.iugocare.com"
}